{
    "generatedAt":  "2026-03-06T20:11:49.2905765-05:00",
    "regular":  {
                    "2018":  [

                             ],
                    "2019":  [

                             ],
                    "2020":  [

                             ],
                    "2021":  [
                                 "./assets/memories/2021/20210811_195803.webp",
                                 "./assets/memories/2021/image1.webp",
                                 "./assets/memories/2021/image0.webp"
                             ],
                    "2022":  [

                             ],
                    "2023":  [

                             ],
                    "2024":  [

                             ],
                    "2025":  [

                             ],
                    "2026":  [

                             ]
                },
    "winter":  {
                   "2023":  [

                            ],
                   "2024":  [

                            ],
                   "2025":  [

                            ],
                   "2026":  [

                            ]
               }
}
